rexplain/__init__.py
rexplain/cli/__init__.py
rexplain/cli/main.py
rexplain/core/__init__.py
rexplain/core/diagram.py
rexplain/core/explainer.py
rexplain/core/generator.py
rexplain/core/parser.py
rexplain/core/tester.py
rexplain-0.3.3.dist-info/METADATA
rexplain-0.3.3.dist-info/WHEEL
rexplain-0.3.3.dist-info/entry_points.txt
rexplain-0.3.3.dist-info/licenses/LICENSE.md
rexplain-0.3.3.dist-info/RECORD
